zszshhh/__init__.py
zszshhh/test1.py
zszshhh/test2.py
zszshhh-1.0.dist-info/LICENSE.txt
zszshhh-1.0.dist-info/METADATA
zszshhh-1.0.dist-info/WHEEL
zszshhh-1.0.dist-info/top_level.txt
zszshhh-1.0.dist-info/RECORD
