Metadata-Version: 2.1
Name: zszshhh
Version: 1.0
Summary: Just Test PyPI Package
Home-page: https://github.com
Author: DMY
Author-email: 2023020560@hrbmu.edu.cn
Requires-Python: >=3.6
License-File: LICENSE.txt
